dotenvy/__init__.py
dotenvy/cli.py
dotenvy/exception.py
dotenvy/parser.py
dotenvy-0.2.0.dist-info/DESCRIPTION.rst
dotenvy-0.2.0.dist-info/METADATA
dotenvy-0.2.0.dist-info/RECORD
dotenvy-0.2.0.dist-info/WHEEL
dotenvy-0.2.0.dist-info/entry_points.txt
dotenvy-0.2.0.dist-info/metadata.json
dotenvy-0.2.0.dist-info/top_level.txt
