Metadata-Version: 1.1
Name: dotenvy
Version: 0.2.0
Summary: Dotenv handler for Python
Home-page: https://github.com/chickenzord/dotenvy
Author: Akhyar Amarullah
Author-email: akhyrul@gmail.com
License: MIT
Download-URL: https://github.com/chickenzord/dotenvy/archive/v0.2.0.tar.gz
Keywords: dotenv,configuration,environment
Platform: UNKNOWN
Classifier: Development Status :: 4 - Beta
Classifier: License :: OSI Approved :: MIT License
Classifier: Intended Audience :: Developers
Classifier: Operating System :: POSIX :: Linux
Classifier: Programming Language :: Python
Classifier: Programming Language :: Python :: 2.7
Classifier: Programming Language :: Python :: 3.3
Classifier: Programming Language :: Python :: 3.4
Classifier: Programming Language :: Python :: 3.5
Classifier: Programming Language :: Python :: 3.6
Classifier: Topic :: Software Development :: Libraries
Classifier: Topic :: Utilities
